openmc_depletion_plotter/__init__.py
openmc_depletion_plotter/_version.py
openmc_depletion_plotter/app.py
openmc_depletion_plotter/integrators.py
openmc_depletion_plotter/launch.py
openmc_depletion_plotter/materials.py
openmc_depletion_plotter/results.py
openmc_depletion_plotter/utils.py
openmc_depletion_plotter-0.4.2.dist-info/LICENSE.txt
openmc_depletion_plotter-0.4.2.dist-info/METADATA
openmc_depletion_plotter-0.4.2.dist-info/WHEEL
openmc_depletion_plotter-0.4.2.dist-info/entry_points.txt
openmc_depletion_plotter-0.4.2.dist-info/top_level.txt
openmc_depletion_plotter-0.4.2.dist-info/RECORD
