Metadata-Version: 2.2
Name: openmc_depletion_plotter
Version: 0.4.2
Summary: Plot the isotopes present during depletion steps.
Author-email: Jonathan Shimwell <mail@jshimwell.com>
License: MIT License
Project-URL: Homepage, https://github.com/fusion-energy/openmc_depletion_plotter
Project-URL: Bug Tracker, https://github.com/fusion-energy/openmc_depletion_plotter/issues
Keywords: dagmc,geometry,plot,slice
Classifier: Programming Language :: Python :: 3
Classifier: License :: OSI Approved :: MIT License
Classifier: Operating System :: OS Independent
Requires-Python: >=3.8
License-File: LICENSE.txt
Requires-Dist: pint
Requires-Dist: plotly
Requires-Dist: numpy
Requires-Dist: matplotlib
Requires-Dist: kaleido
Provides-Extra: tests
Requires-Dist: pytest; extra == "tests"
Provides-Extra: gui
Requires-Dist: streamlit; extra == "gui"
